jamm/__init__.py
jamm/bank.py
jamm/charge.py
jamm/client.py
jamm/contract.py
jamm/customer.py
jamm/errors.py
jamm/healthcheck.py
jamm/import_hook.py
jamm/payment.py
jamm/version.py
jamm/webhook.py
jamm/api/__init__.py
jamm/api/bank_api.py
jamm/api/client.py
jamm/api/customer_api.py
jamm/api/healthcheck_api.py
jamm/api/payment_api.py
jamm/api/validation.py
jamm/auth/__init__.py
jamm/auth/oauth.py
jamm/config/__init__.py
jamm/config/settings.py
jamm/environment/__init__.py
jamm/environment/env.py
jamm/http/__init__.py
jamm/http/client.py
jamm/models/__init__.py
jamm/models/banking.py
jamm/models/common.py
jamm/models/customer.py
jamm/models/healthcheck.py
jamm/models/payment.py
jamm-0.3.0.dist-info/licenses/LICENSE
jamm-0.3.0.dist-info/METADATA
jamm-0.3.0.dist-info/WHEEL
jamm-0.3.0.dist-info/top_level.txt
jamm-0.3.0.dist-info/RECORD
