Metadata-Version: 2.4
Name: jamm
Version: 0.3.0
Summary: Jamm API Python SDK
Author: Jamm Team
License: MIT
Project-URL: Homepage, https://jamm-pay.jp
Project-URL: Bug Tracker, https://jamm-pay.jp
Project-URL: Documentation, https://docs.jamm.pay/sdk/python
Project-URL: Source, https://jamm-pay.jp
Classifier: Development Status :: 4 - Beta
Classifier: Intended Audience :: Developers
Classifier: Programming Language :: Python :: 3
Classifier: Programming Language :: Python :: 3.9
Classifier: Programming Language :: Python :: 3.10
Classifier: Programming Language :: Python :: 3.11
Classifier: Programming Language :: Python :: 3.12
Classifier: Programming Language :: Python :: 3.13
Classifier: License :: OSI Approved :: MIT License
Classifier: Operating System :: OS Independent
Requires-Python: >=3.9
License-File: LICENSE
Requires-Dist: grpcio>=1.73.0
Requires-Dist: protobuf>=6.31.1
Requires-Dist: pydantic<2.12.0,>=2.11.7
Requires-Dist: requests>=2.32.4
Provides-Extra: dev
Requires-Dist: pytest>=7.0.0; extra == "dev"
Requires-Dist: pytest-cov>=4.1.0; extra == "dev"
Requires-Dist: black>=23.0.0; extra == "dev"
Requires-Dist: isort>=5.12.0; extra == "dev"
Requires-Dist: mypy>=1.0.0; extra == "dev"
Requires-Dist: flake8>=6.0.0; extra == "dev"
Requires-Dist: types-protobuf>=5.29.0; extra == "dev"
Requires-Dist: types-requests>=2.32.0; extra == "dev"
Requires-Dist: pytest>=7.0.0; extra == "dev"
Requires-Dist: pytest-cov>=4.1.0; extra == "dev"
Requires-Dist: Faker>=37.4.0; extra == "dev"
Requires-Dist: protoc-gen-openapiv2>=0.0.1; extra == "dev"
Dynamic: license-file
